{
  "configurations": [
    {
      "name": "FCEditor Editor Win64 Development (FC)",
      "compilerPath": "C:\\Program Files\\Microsoft Visual Studio\\2022\\Community\\VC\\Tools\\MSVC\\14.44.35207\\bin\\Hostx64\\x64\\cl.exe",
      "cStandard": "c17",
      "cppStandard": "c++20",
      "intelliSenseMode": "msvc-x64",
      "compileCommands": [
        "W:\\GameDev\\FallenCompass\\FC\\.vscode\\compileCommands_FC.json"
      ]
    },
    {
      "name": "Win32",
      "compilerPath": "C:\\Program Files\\Microsoft Visual Studio\\2022\\Community\\VC\\Tools\\MSVC\\14.44.35207\\bin\\Hostx64\\x64\\cl.exe",
      "cStandard": "c17",
      "cppStandard": "c++20",
      "intelliSenseMode": "msvc-x64",
      "compileCommands": [
        "W:\\GameDev\\FallenCompass\\FC\\.vscode\\compileCommands_Default.json"
      ]
    },
    {
      "name": "Windows-MSVC",
      "intelliSenseMode": "windows-msvc-x64",
      "compilerPath": "C:/Program Files/Microsoft Visual Studio/2022/Community/VC/Tools/MSVC/<VERSION>/bin/Hostx64/x64/cl.exe",
      "cStandard": "c11",
      "cppStandard": "c++17",
      "includePath": [
        "${workspaceFolder}/Source/**",
        "W:/GameDev/FallenCompass/FC/Source/**",
        "W:/GameDev/UE_5.7/Engine/Source/**",
        "W:/GameDev/UE_5.7/Engine/Source/Runtime/**",
        "W:/GameDev/UE_5.7/Engine/Source/ThirdParty/**",
        "W:/GameDev/UE_5.7/Engine/Source/Developer/**"
      ],
      "browse": {
        "path": [
          "${workspaceFolder}/Source",
          "W:/GameDev/UE_5.7/Engine/Source"
        ],
        "limitSymbolsToIncludedHeaders": false
      },
      "defines": ["WIN32", "_WINDOWS", "UNICODE", "_UNICODE"]
    }
  ],
  "version": 4
}
